{
  "https://yuyu-tei.jp/sell/hocg/card/hbp05/10031": [ [ "2026-05-10T21:07:03.87768647Z", { "y": 30 } ] ],
  "https://yuyu-tei.jp/sell/hocg/card/hbp05/10032": [ [ "2026-05-10T21:07:03.877425287Z", { "y": 180 } ] ],
  "https://yuyu-tei.jp/sell/hocg/card/promo-hbp10/10160": [ [ "2026-05-10T21:07:03.877524156Z", { "y": 1980 } ] ],
  "https://www.tcgplayer.com/product/689976": [ [ "2026-05-10T21:07:04.961815252Z", { "d": 15 } ] ],
  "https://www.tcgplayer.com/product/689977": [ [ "2026-05-10T21:07:04.961815422Z", { "d": 410 } ] ]
}